COPYING
MANIFEST.in
README.rst
buildout.cfg
develop.cfg
pyproject.toml
requirements.txt
setup.py
version.txt
bob/__init__.py
bob.ip.qualitymeasure.egg-info/PKG-INFO
bob.ip.qualitymeasure.egg-info/SOURCES.txt
bob.ip.qualitymeasure.egg-info/dependency_links.txt
bob.ip.qualitymeasure.egg-info/entry_points.txt
bob.ip.qualitymeasure.egg-info/requires.txt
bob.ip.qualitymeasure.egg-info/top_level.txt
bob/ip/__init__.py
bob/ip/qualitymeasure/__init__.py
bob/ip/qualitymeasure/galbally_iqm_features.py
bob/ip/qualitymeasure/main.cpp
bob/ip/qualitymeasure/msu_iqa_features.py
bob/ip/qualitymeasure/tan_specular_highlights.cpp
bob/ip/qualitymeasure/test.py
bob/ip/qualitymeasure/version.cpp
bob/ip/qualitymeasure/data/old_man.ppm
bob/ip/qualitymeasure/data/old_man_diffuse.ppm
bob/ip/qualitymeasure/data/real_client001_android_SD_scene01.mp4
bob/ip/qualitymeasure/data/real_client001_android_SD_scene01_ref_feats.h5
bob/ip/qualitymeasure/data/toys.ppm
bob/ip/qualitymeasure/data/toys_diffuse.ppm
bob/ip/qualitymeasure/script/__init__.py
bob/ip/qualitymeasure/script/compute_qualitymeasures.py
bob/ip/qualitymeasure/script/remove_highlights.py
doc/conf.py
doc/guide.rst
doc/index.rst
doc/links.rst
doc/py_api.rst
doc/img/favicon.ico
doc/img/logo.png