Metadata-Version: 2.1
Name: bob.ip.qualitymeasure
Version: 1.1.8
Summary: Image-quality feature-extractors for PAD applications
Home-page: http://gitlab.idiap.ch/bob/bob.ip.qualitymeasure
Author: Sushil Bhattacharjee
Author-email: sushil.bhattacharjee@idiap.ch
Maintainer: David Geissbuhler
Maintainer-email: david.geissbuhler@idiap.ch
License: GPLv3
Keywords: bob,image-quality,face
Platform: UNKNOWN
Classifier: Framework :: Bob
Classifier: Development Status :: 4 - Beta
Classifier: Intended Audience :: Developers
Classifier: License :: OSI Approved :: GNU General Public License v3 (GPLv3)
Classifier: Natural Language :: English
Classifier: Programming Language :: Python
Classifier: Programming Language :: Python :: 3
Classifier: Topic :: Software Development :: Libraries :: Python Modules
License-File: COPYING
